setup.py
client/__init__.py
client/client.py
client/client/__init__.py
client/client/add_contact.py
client/client/database.py
client/client/del_contact.py
client/client/main_window.py
client/client/main_window_conv.py
client/client/start_dialog.py
client/client/transport.py
client/common/__init__.py
client/common/decos.py
client/common/descryptors.py
client/common/errors.py
client/common/metaclasses.py
client/common/utils.py
client/common/variables.py
client/doc/__init__.py
client/doc/source/__init__.py
client/doc/source/conf.py
client/logs/__init__.py
client/logs/configs/__init__.py
client/logs/configs/client_log_config.py
client/logs/configs/server_log_config.py
client/unit_tests/__init__.py
client/unit_tests/test_client.py
client/unit_tests/test_server.py
mess_client_app.egg-info/PKG-INFO
mess_client_app.egg-info/SOURCES.txt
mess_client_app.egg-info/dependency_links.txt
mess_client_app.egg-info/requires.txt
mess_client_app.egg-info/top_level.txt