Metadata-Version: 1.0
Name: mess-client-app
Version: 0.0.1
Summary: mess_client_app
Home-page: UNKNOWN
Author: KosarevDV
Author-email: dlinnii21@gmail.com
License: UNKNOWN
Platform: UNKNOWN
